__init__.py
sumTwo.py
sumTwo-1.0.0.dist-info/METADATA
sumTwo-1.0.0.dist-info/WHEEL
sumTwo-1.0.0.dist-info/top_level.txt
sumTwo-1.0.0.dist-info/RECORD
