Metadata-Version: 2.2
Name: sumTwo
Version: 1.0.0
Summary: Sum two number
Author-email: thangtd <trandinhthangv1@gmail.com>
Keywords: sumtwo
Classifier: License :: OSI Approved :: MIT License
Classifier: Programming Language :: Python
Classifier: Programming Language :: Python :: 3
Classifier: Operating System :: MacOS :: MacOS X
Classifier: Operating System :: Microsoft :: Windows
Classifier: Intended Audience :: Education
